{
  "$schema": "https://developer.microsoft.com/json-schemas/fabric/item/report/definition/visualContainer/2.1.0/schema.json",
  "name": "b268ea3e0e0593abb0c8",
  "position": {
    "x": 12.943820224719104,
    "y": 17.797752808988861,
    "z": 1000,
    "height": 59.865168539325843,
    "width": 200.62921348314606,
    "tabOrder": 8000
  },
  "visual": {
    "visualType": "slicer",
    "query": {
      "queryState": {
        "Values": {
          "projections": [
            {
              "field": {
                "Column": {
                  "Expression": {
                    "SourceRef": {
                      "Entity": "QCMS_DEFECTS"
                    }
                  },
                  "Property": "Created_Year"
                }
              },
              "queryRef": "QCMS_DEFECTS.Created_Year",
              "nativeQueryRef": "Created_Year",
              "active": true
            }
          ]
        }
      }
    },
    "objects": {
      "data": [
        {
          "properties": {
            "mode": {
              "expr": {
                "Literal": {
                  "Value": "'Dropdown'"
                }
              }
            }
          }
        }
      ],
      "general": [
        {
          "properties": {
            "filter": {
              "filter": {
                "Version": 2,
                "From": [
                  {
                    "Name": "q",
                    "Entity": "QCMS_DEFECTS",
                    "Type": 0
                  }
                ],
                "Where": [
                  {
                    "Condition": {
                      "In": {
                        "Expressions": [
                          {
                            "Column": {
                              "Expression": {
                                "SourceRef": {
                                  "Source": "q"
                                }
                              },
                              "Property": "Created_Year"
                            }
                          }
                        ],
                        "Values": [
                          [
                            {
                              "Literal": {
                                "Value": "2025L"
                              }
                            }
                          ]
                        ]
                      }
                    }
                  }
                ]
              }
            }
          }
        }
      ],
      "header": [
        {
          "properties": {
            "text": {
              "expr": {
                "Literal": {
                  "Value": "'Year'"
                }
              }
            },
            "fontColor": {
              "solid": {
                "color": {
                  "expr": {
                    "ThemeDataColor": {
                      "ColorId": 1,
                      "Percent": 0.2
                    }
                  }
                }
              }
            }
          }
        }
      ]
    },
    "drillFilterOtherVisuals": true
  },
  "parentGroupName": "6800935f6d80067c8b7c"
}