{
  "$schema": "https://developer.microsoft.com/json-schemas/fabric/item/report/definition/visualContainer/2.1.0/schema.json",
  "name": "62661250993dc8c1e46e",
  "position": {
    "x": 983.7303370786517,
    "y": 121.34831460674157,
    "z": 11000,
    "height": 59.865168539325843,
    "width": 184.44943820224719,
    "tabOrder": 11000
  },
  "visual": {
    "visualType": "slicer",
    "query": {
      "queryState": {
        "Values": {
          "projections": [
            {
              "field": {
                "Column": {
                  "Expression": {
                    "SourceRef": {
                      "Entity": "QCMS_DEFECTS"
                    }
                  },
                  "Property": "Formatted_Created_Date"
                }
              },
              "queryRef": "QCMS_DEFECTS.Formatted_Created_Date",
              "nativeQueryRef": "Formatted_Created_Date",
              "active": true
            }
          ]
        }
      }
    },
    "objects": {
      "data": [
        {
          "properties": {
            "mode": {
              "expr": {
                "Literal": {
                  "Value": "'Dropdown'"
                }
              }
            }
          }
        }
      ],
      "header": [
        {
          "properties": {
            "text": {
              "expr": {
                "Literal": {
                  "Value": "'Date'"
                }
              }
            },
            "fontColor": {
              "solid": {
                "color": {
                  "expr": {
                    "ThemeDataColor": {
                      "ColorId": 1,
                      "Percent": 0.2
                    }
                  }
                }
              }
            }
          }
        }
      ],
      "general": [
        {
          "properties": {}
        }
      ]
    },
    "drillFilterOtherVisuals": true
  }
}